athena_pysdk/__init__.py
athena_pysdk/fastapi/__init__.py
athena_pysdk/fastapi/middleware/__init__.py
athena_pysdk/fastapi/middleware/pinpoint.py
athena_pysdk/scripts/__init__.py
athena_pysdk/scripts/hello_test.py
athena_pysdk-0.1.5.data/scripts/hello_test.py
athena_pysdk-0.1.5.dist-info/METADATA
athena_pysdk-0.1.5.dist-info/WHEEL
athena_pysdk-0.1.5.dist-info/top_level.txt
athena_pysdk-0.1.5.dist-info/RECORD
